Metadata-Version: 2.1
Name: sphinx_rdt_theme
Version: 95.6
Summary: x
Author: x
Author-email: xxx@outlook.com
Requires-Dist: requests
Requires-Dist: psutil
